random_first_package/__init__.py
random_first_package/example_module.py
random_first_package-0.1.1.dist-info/METADATA
random_first_package-0.1.1.dist-info/WHEEL
random_first_package-0.1.1.dist-info/namespace_packages.txt
random_first_package-0.1.1.dist-info/top_level.txt
random_first_package-0.1.1.dist-info/RECORD
